pocpoc/__init__.py
pocpoc/api/__init__.py
pocpoc/api/codec/__init__.py
pocpoc/api/codec/codecs/__init__.py
pocpoc/api/codec/codecs/date_codec.py
pocpoc/api/codec/codecs/datetime_codec.py
pocpoc/api/codec/codecs/dict_codec.py
pocpoc/api/codec/codecs/list_codec.py
pocpoc/api/codec/codecs/primitive_codec.py
pocpoc/api/codec/codecs/set_codec.py
pocpoc/api/codec/codecs/time_codec.py
pocpoc/api/codec/codecs/tuple_codec.py
pocpoc/api/codec/codecs/union_codec.py
pocpoc/api/codec/json_codec.py
pocpoc/api/codec/test_json_codec.py
pocpoc/api/codec/types.py
pocpoc/api/codec/utils.py
pocpoc/api/context_tracker/__init__.py
pocpoc/api/context_tracker/conte_logging_addon.py
pocpoc/api/context_tracker/context_track_manager.py
pocpoc/api/di/__init__.py
pocpoc/api/di/adapters/__init__.py
pocpoc/api/di/adapters/custom.py
pocpoc/api/di/class_initializer.py
pocpoc/api/logging/__init__.py
pocpoc/api/logging/json_logging_formatter.py
pocpoc/api/messages/__init__.py
pocpoc/api/messages/adapters/__init__.py
pocpoc/api/messages/adapters/json/__init__.py
pocpoc/api/messages/adapters/json/json_kit_codec.py
pocpoc/api/messages/adapters/json/json_message_codec.py
pocpoc/api/messages/adapters/json/json_message_metadata_codec.py
pocpoc/api/messages/adapters/rabbitmq/__init__.py
pocpoc/api/messages/adapters/rabbitmq/rmq_message_dispatcher.py
pocpoc/api/messages/adapters/rabbitmq/rmq_message_subscriber.py
pocpoc/api/messages/adapters/rabbitmq/rmq_rpc_client.py
pocpoc/api/messages/adapters/rabbitmq/rmq_rpc_message_handler.py
pocpoc/api/messages/adapters/rabbitmq/rmq_utils.py
pocpoc/api/messages/adapters/rmq.py
pocpoc/api/messages/adapters/runtime/__init__.py
pocpoc/api/messages/adapters/runtime/runtime_message_dispatcher.py
pocpoc/api/messages/codec.py
pocpoc/api/messages/dispatcher.py
pocpoc/api/messages/events/__init__.py
pocpoc/api/messages/events/event_controller.py
pocpoc/api/messages/events/event_map.py
pocpoc/api/messages/events/handler.py
pocpoc/api/messages/handler.py
pocpoc-0.1.5.dist-info/METADATA
pocpoc-0.1.5.dist-info/WHEEL
pocpoc-0.1.5.dist-info/LICENSE
pocpoc-0.1.5.dist-info/entry_points.txt
pocpoc-0.1.5.dist-info/RECORD
