Metadata-Version: 2.1
Name: pocpoc
Version: 0.1.5
Summary: 
Author: Lucas Silva
Author-email: lucas76leonardo@gmail.com
Requires-Python: >=3.7,<4.0
Classifier: Programming Language :: Python :: 3
Classifier: Programming Language :: Python :: 3.7
Classifier: Programming Language :: Python :: 3.8
Classifier: Programming Language :: Python :: 3.9
Classifier: Programming Language :: Python :: 3.10
Classifier: Programming Language :: Python :: 3.11
Provides-Extra: debugging
Provides-Extra: rabbitmq
Provides-Extra: sqa
Requires-Dist: alembic (>=1.8.1,<2.0.0) ; extra == "sqa"
Requires-Dist: click (==8.1.3)
Requires-Dist: colorlog (>=6.7.0,<7.0.0) ; extra == "debugging"
Requires-Dist: pika (>=1.3.1,<2.0.0) ; extra == "rabbitmq"
Requires-Dist: sqlalchemy (>=1.4.44,<2.0.0) ; extra == "sqa"
